Aofex_SDK/Aofex_SDK.py
Aofex_SDK/__init__.py
Aofex_SDK-1.1.1.dist-info/LICENSE
Aofex_SDK-1.1.1.dist-info/METADATA
Aofex_SDK-1.1.1.dist-info/WHEEL
Aofex_SDK-1.1.1.dist-info/top_level.txt
Aofex_SDK-1.1.1.dist-info/RECORD
