Metadata-Version: 2.1
Name: Aofex-SDK
Version: 1.1.1
Summary: Aofex SDK
Home-page: https://github.com/monk-after-90s/Aofex_SDK.git
Author: Antas
Author-email: 
License: UNKNOWN
Platform: UNKNOWN
Classifier: Programming Language :: Python :: 3
Classifier: License :: OSI Approved :: MIT License
Classifier: Operating System :: OS Independent
Requires-Python: >=3.6
